hiresynth_object_store_python-0.1.4.dist-info/METADATA
hiresynth_object_store_python-0.1.4.dist-info/WHEEL
object_store/__init__.py
object_store/_internal.pyi
object_store/arrow.py
object_store/py.typed
object_store/_internal.abi3.so
hiresynth_object_store_python-0.1.4.dist-info/RECORD
